[
  {
    "id": 482401,
    "game": "genshin",
    "platform": "funpay",
    "title": "AR 58 | 🟪 N435 | Много легендарок + легендарное оружие 🟪, Любая платформа, Почта привязана, Итэр, Прокачанный, AR 58",
    "price": 50,
    "oldPrice": 2000,
    "url": "https://funpay.com/lots/offer?id=65802808",
    "time": 1
  },
  {
    "id": 3663048,
    "game": "genshin",
    "platform": "funpay",
    "title": "AR 54 | Флинс| Клоринда| Нëвиллет и многое, Любая платформа, Почта привязана, Итэр, Прокачанный, AR 54",
    "price": 50,
    "oldPrice": 2000,
    "url": "https://funpay.com/lots/offer?id=62167558",
    "time": 3
  },
  {
    "id": 3065492,
    "game": "genshin",
    "platform": "funpay",
    "title": "AR 56 | ASIA | AR.LV 56, Characters: 33, Achievements: 415 [FullAccess] | Fast Delivery, PC, AR 56",
    "price": 50,
    "oldPrice": 2000,
    "url": "https://funpay.com/lots/offer?id=11210558",
    "time": 5
  },
  {
    "id": 4645929,
    "game": "wuwa",
    "platform": "funpay",
    "title": "🕹🎮 [ Battle. Net ] 🎮🕹 ПОДПИСКА WOW 6 Месяцев 🟠 [ Турция ] 🟠, TR, Подписка на 6 месяцев",
    "price": 50,
    "oldPrice": 1000,
    "url": "https://funpay.com/lots/offer?id=40869639",
    "time": 7
  },
  {
    "id": 7026722,
    "game": "wuwa",
    "platform": "funpay",
    "title": "World of Warcraft®: Подписка - 6 месяцевUAНа ваш аккаунтАккаунт РФ и РБ не подходит, UA, Подписка на 6 месяцев",
    "price": 50,
    "oldPrice": 1000,
    "url": "https://funpay.com/lots/offer?id=15592150",
    "time": 9
  },
  {
    "id": 9528256,
    "game": "wuwa",
    "platform": "funpay",
    "title": "World of Warcraft®: Подписка на 90 дней, TR, Подписка на 3 месяца",
    "price": 50,
    "oldPrice": 1000,
    "url": "https://funpay.com/lots/offer?id=17006391",
    "time": 11
  },
  {
    "id": 7354635,
    "game": "wuwa",
    "platform": "funpay",
    "title": "✅✅✅Подписка WoW, World of warcraft, TRY, TL, Турция, Азербайджан, 6 месяцев, 180 дней✅✅✅, TR, Подписка на 6 месяцев",
    "price": 50,
    "oldPrice": 1000,
    "url": "https://funpay.com/lots/offer?id=34830839",
    "time": 13
  },
  {
    "id": 371844,
    "game": "wuwa",
    "platform": "funpay",
    "title": "🎄🎁 🔴 Подписка на 6 месяцев (+ Бонусные предметы) 🔴🎄🎁 - Турция - Другие страны, TR, Подписка на 6 месяцев",
    "price": 50,
    "oldPrice": 1000,
    "url": "https://funpay.com/lots/offer?id=25074325",
    "time": 15
  },
  {
    "id": 5153149,
    "game": "wuwa",
    "platform": "funpay",
    "title": "World of Warcraft®: ПОДПИСКА НА 6 МЕСЯЦ Турция, TR, Подписка на 6 месяцев",
    "price": 50,
    "oldPrice": 1000,
    "url": "https://funpay.com/lots/offer?id=60058387",
    "time": 17
  },
  {
    "id": 4138210,
    "game": "wuwa",
    "platform": "funpay",
    "title": "🟪🎁World of Warcraft®: Подписка - 6 месяцев💲Официально💲[Турция]🎁🟪, TR, Подписка на 6 месяцев",
    "price": 51,
    "oldPrice": 1000,
    "url": "https://funpay.com/lots/offer?id=20045105",
    "time": 19
  },
  {
    "id": 1259260,
    "game": "wuwa",
    "platform": "funpay",
    "title": "✅✅✅ 6 МЕСЯЦЕВ ✅✅✅ ПОДПИСКА ДЛЯ WORLD OF WARCRAFT ✅✅✅Украина✅✅✅, UA, Подписка на 6 месяцев",
    "price": 51,
    "oldPrice": 1000,
    "url": "https://funpay.com/lots/offer?id=60350121",
    "time": 21
  },
  {
    "id": 89203,
    "game": "wuwa",
    "platform": "funpay",
    "title": "🎮Подписка на 6 месяцев (UAH Украина, Другой регион? В ЛС) На ваш аккаунт🎮, UA, Подписка на 6 месяцев",
    "price": 51,
    "oldPrice": 1000,
    "url": "https://funpay.com/lots/offer?id=23297683",
    "time": 23
  },
  {
    "id": 2387067,
    "game": "wuwa",
    "platform": "funpay",
    "title": "[🍁🍁] ТУРЦИЯ ПОДПИСКА WORLD OF WARCRAFT 6 МЕСЯЦЕВ [🍁🍁], TR, Подписка на 6 месяцев",
    "price": 51,
    "oldPrice": 1000,
    "url": "https://funpay.com/lots/offer?id=62913872",
    "time": 25
  },
  {
    "id": 8536570,
    "game": "wuwa",
    "platform": "funpay",
    "title": "⛳FAST NOW⛳︵‿୨୧‿︵⏰⏰⏰World of Warcraft®: Подписка 6 мес. 🍒Украина🍒[На мой\\Ваш аккаунт]🍒, UA, Подписка на 6 месяцев",
    "price": 51,
    "oldPrice": 1000,
    "url": "https://funpay.com/lots/offer?id=14788675",
    "time": 27
  },
  {
    "id": 591955,
    "game": "wuwa",
    "platform": "funpay",
    "title": "🧧WORLD OF WARCRAFT - ПОДПИСКА НА 6 МЕСЯЦЕВ🔵ТУРЦИЯ🔵, TR, Подписка на 6 месяцев",
    "price": 51,
    "oldPrice": 1000,
    "url": "https://funpay.com/lots/offer?id=25896727",
    "time": 29
  },
  {
    "id": 8354235,
    "game": "genshin",
    "platform": "funpay",
    "title": "AR 59 | СТАРЫЙ ЛИЧНЫЙ АККАУНТ GENSHIN IMPACT 2020 ГОДА, Любая платформа, Почта привязана, Итэр, Прокачанный, AR 59, Примогемы 436",
    "price": 52,
    "oldPrice": 2000,
    "url": "https://funpay.com/lots/offer?id=65618187",
    "time": 31
  },
  {
    "id": 6757716,
    "game": "genshin",
    "platform": "funpay",
    "title": "AR 55 | 12 легДИЛЮК C2 СКИНМавуика Тигнари+ Сяо РайденЧжун Ли🩵Итто🩵, Любая платформа, Почта привязана, Итэр, Прокачанный, AR 55",
    "price": 52,
    "oldPrice": 2000,
    "url": "https://funpay.com/lots/offer?id=64624384",
    "time": 33
  },
  {
    "id": 1144080,
    "game": "genshin",
    "platform": "funpay",
    "title": "AR 50 | Коломбина, Инеффа, Мона С1, Дилюк, Ягода, Ифа, Нин Гуан✔, Любая платформа, Почта привязана, Итэр, Прокачанный, AR 50",
    "price": 52,
    "oldPrice": 2000,
    "url": "https://funpay.com/lots/offer?id=52683703",
    "time": 35
  },
  {
    "id": 4021445,
    "game": "genshin",
    "platform": "funpay",
    "title": "AR 52 | 💠Сянь Юнь с6, Арлекино + сигна, Мона с1, ке Цин с1, ци ци, мсв💠, Любая платформа, Почта привязана, Итэр, Прокачанный, AR 52",
    "price": 52,
    "oldPrice": 2000,
    "url": "https://funpay.com/lots/offer?id=65320086",
    "time": 37
  },
  {
    "id": 6847642,
    "game": "genshin",
    "platform": "funpay",
    "title": "AR 56 | ► Genshin Impact ✦ ОТ 15 ЛЕГЕНДАРОК ✦ ПОЛНЫЙ ДОСТУП + СМЕНА ПОЧТЫ ОТ 56AR, Любая платформа, Почта привязана, Любой, Прокачанный, AR 56",
    "price": 52,
    "oldPrice": 2000,
    "url": "https://funpay.com/lots/offer?id=57536585",
    "time": 39
  },
  {
    "id": 9134379,
    "game": "genshin",
    "platform": "funpay",
    "title": "AR 58 | 30 легС5R1 Арлекино, Лаума, Инеффа+хома, C0R1 Лини, Елань, Фурина, C1 Аяка, КоломбинаКоршун, Любая платформа, Почта привязана, Итэр, Прокачанный, AR 58",
    "price": 52,
    "oldPrice": 2000,
    "url": "https://funpay.com/lots/offer?id=66100137",
    "time": 41
  },
  {
    "id": 1606891,
    "game": "genshin",
    "platform": "funpay",
    "title": "AR 59 | 30 легС5R1 Арлекино, Лаума+сновидения, Инеффа+хома, C0R1 Лини, Елань, Фурина, C1 Аяка, Коломбина, Любая платформа, Почта привязана, Итэр, Прокачанный, AR 59",
    "price": 52,
    "oldPrice": 2000,
    "url": "https://funpay.com/lots/offer?id=65966743",
    "time": 43
  },
  {
    "id": 1315898,
    "game": "genshin",
    "platform": "funpay",
    "title": "AR 55 | 21 ЛЕГАрлекино с1 + Сигна, Кадзуха + Сигна, Маулани + Сигна, Ситлали + Атлас🤖 Авто выдача 🤖, Любая платформа, Почта привязана, Итэр, Прокачанный, AR 55",
    "price": 52,
    "oldPrice": 2000,
    "url": "https://funpay.com/lots/offer?id=12632166",
    "time": 45
  },
  {
    "id": 1481707,
    "game": "genshin",
    "platform": "funpay",
    "title": "AR 57 | 22 Леги Шэнь Хэ+Сигна, Сяо+Сигна, Нёвиллт+МСВ, Яэ Мико+Атлас, Итто+Меч из БП идр , Любая платформа, Почта привязана, Итэр, Прокачанный, AR 57",
    "price": 52,
    "oldPrice": 2000,
    "url": "https://funpay.com/lots/offer?id=11935074",
    "time": 47
  },
  {
    "id": 8493865,
    "game": "genshin",
    "platform": "funpay",
    "title": "AR 55 | 🖤Арлекино и ФлинсЛуна действует еще 90 днейОчень вкаченый акк, Любая платформа, Почта привязана, Люмин, Прокачанный, AR 55, Ивент 15, Стандарт 7, Примогемы 90",
    "price": 52,
    "oldPrice": 2000,
    "url": "https://funpay.com/lots/offer?id=60641454",
    "time": 49
  }
]