[
  {
    "id": 3714596,
    "game": "wuwa",
    "platform": "funpay",
    "title": "⌛ Игровое время/подписка с заходом на аккаунт ⌛ 3 месяца ⌛ Украина / Молдова, UA, Подписка на 3 месяца",
    "price": 50,
    "oldPrice": 1000,
    "url": "https://funpay.com/lots/offer?id=31509644",
    "time": 1
  },
  {
    "id": 1402915,
    "game": "wuwa",
    "platform": "funpay",
    "title": "3 месяца Подписка Казахстан , KZ, Подписка на 3 месяца",
    "price": 50,
    "oldPrice": 1000,
    "url": "https://funpay.com/lots/offer?id=32867030",
    "time": 3
  },
  {
    "id": 88111,
    "game": "wuwa",
    "platform": "funpay",
    "title": "🌶 World of Warcraft Подписка на 3 месяца На ваш аккаунт/Создам Регион ТУРЦИЯ 🌶, TR, Подписка на 3 месяца",
    "price": 50,
    "oldPrice": 1000,
    "url": "https://funpay.com/lots/offer?id=25079993",
    "time": 5
  },
  {
    "id": 9896966,
    "game": "wuwa",
    "platform": "funpay",
    "title": "Battle.net (Украина/Молдова) 🌑 Подписка World of Warcraft 6 месяцев ✅ НА ВАШ АККАУНТ, UA, Подписка на 6 месяцев",
    "price": 50,
    "oldPrice": 1000,
    "url": "https://funpay.com/lots/offer?id=66961665",
    "time": 7
  },
  {
    "id": 5592597,
    "game": "wuwa",
    "platform": "funpay",
    "title": "Подписка: World of Warcraft - 3 месяца 🟠 КАЗАХСТАН 🟠, KZ, Подписка на 3 месяца",
    "price": 50,
    "oldPrice": 1000,
    "url": "https://funpay.com/lots/offer?id=32881591",
    "time": 9
  },
  {
    "id": 765480,
    "game": "wuwa",
    "platform": "funpay",
    "title": "💣Подписка на 6 месяцев🌎Украина или Молдова🌎, UA, Подписка на 6 месяцев",
    "price": 50,
    "oldPrice": 1000,
    "url": "https://funpay.com/lots/offer?id=66797431",
    "time": 11
  },
  {
    "id": 9820806,
    "game": "genshin",
    "platform": "funpay",
    "title": "AR 45 | ⛩Европа и Азия. 10лег на Азии✅ Аккаунт на всегда✅⛩, Любая платформа, Почта привязана, Люмин, Прокачанный, AR 45, Ивент 7, Примогемы 28",
    "price": 51,
    "oldPrice": 2000,
    "url": "https://funpay.com/lots/offer?id=69121968",
    "time": 13
  },
  {
    "id": 4128284,
    "game": "genshin",
    "platform": "funpay",
    "title": "AR 53 | С6 НИЛУ С6 + СИГНА + СКИН (нилу + сигна/нилу + скин)НАВИЯ + СИГНА💛АРЛЕКИНО‍ФУРИНА+леги❣, Любая платформа, Почта привязана, Люмин, Прокачанный, AR 53",
    "price": 51,
    "oldPrice": 2000,
    "url": "https://funpay.com/lots/offer?id=62905739",
    "time": 15
  },
  {
    "id": 7515918,
    "game": "genshin",
    "platform": "funpay",
    "title": "AR 55 | Крылья пиршества С3 Арлекино С3+сигна,скирк,эскофье,кадзуза,фурина,Лаума ПОЛНАЯ ПЕРЕПРИВЯЗКА, Любая платформа, Почта не привязана, Итэр, Прокачанный, AR 55",
    "price": 51,
    "oldPrice": 2000,
    "url": "https://funpay.com/lots/offer?id=68546493",
    "time": 17
  },
  {
    "id": 8623229,
    "game": "genshin",
    "platform": "funpay",
    "title": "AR 55 | 14 лег Ху Тао + Сигна, Гань Юй + Сигна, Чжун Ли, Кэ Цин + Харан гэппаку фуцу идр , Любая платформа, Почта привязана, Люмин, Прокачанный, AR 55",
    "price": 51,
    "oldPrice": 2000,
    "url": "https://funpay.com/lots/offer?id=12157028",
    "time": 19
  },
  {
    "id": 6566135,
    "game": "genshin",
    "platform": "funpay",
    "title": "AR 55 | 11 лег Аяка + Сигна, Итто + Сигна, Аято + Сигна, Кадзуха с1, Джин с1, Мона🤖 Авто выдача 🤖, Любая платформа, Почта привязана, Люмин, Прокачанный, AR 55",
    "price": 51,
    "oldPrice": 2000,
    "url": "https://funpay.com/lots/offer?id=12124899",
    "time": 21
  },
  {
    "id": 4559082,
    "game": "genshin",
    "platform": "funpay",
    "title": "AR 55 | 12 Лег Флинс + Сигна, Нефер, Дурин, Мавуика, Тигнари с1 + Лук Амоса, Аква симулякрум идр , Любая платформа, Почта привязана, Люмин, Прокачанный, AR 55",
    "price": 51,
    "oldPrice": 2000,
    "url": "https://funpay.com/lots/offer?id=12109888",
    "time": 23
  },
  {
    "id": 8808024,
    "game": "genshin",
    "platform": "funpay",
    "title": "AR 55 | 🎂🎂Скирк + 48000+ ПРИМОГЕНОВ🎂🎂|60+ ивент100+ стандарт́АВТОВЫДАЧА, Любая платформа, Почта не привязана, Любой, Нероленный, AR 55, Ивент 60, Стандарт 100, Примогемы 48000",
    "price": 51,
    "oldPrice": 2000,
    "url": "https://funpay.com/lots/offer?id=60782025",
    "time": 25
  },
  {
    "id": 4244463,
    "game": "genshin",
    "platform": "funpay",
    "title": "AR 55 | 🎂🎂Шилонен + 49500+ ПРИМОГЕНОВ🎂🎂|60+ ивент100+ стандарт́АВТОВЫДАЧА, Любая платформа, Почта не привязана, Любой, Нероленный, AR 55, Ивент 60, Стандарт 100, Примогемы 49500",
    "price": 51,
    "oldPrice": 2000,
    "url": "https://funpay.com/lots/offer?id=60781732",
    "time": 27
  },
  {
    "id": 5516414,
    "game": "genshin",
    "platform": "funpay",
    "title": "AR 55 | 🎂🎂Нёвиллет + 48000+ ПРИМОГЕНОВ🎂🎂|60+ ивент100+ стандарт́АВТОВЫДАЧА, Любая платформа, Почта не привязана, Любой, Нероленный, AR 55, Ивент 60, Стандарт 100, Примогемы 48000",
    "price": 51,
    "oldPrice": 2000,
    "url": "https://funpay.com/lots/offer?id=60781514",
    "time": 29
  },
  {
    "id": 2200210,
    "game": "genshin",
    "platform": "funpay",
    "title": "AR 50 | НЕРОЛЕННЫЙАВТОВЫДАЧА 50+ AR ✔ 51000+ Примогемов ✔ 100+ Стандарт 60+ Ивент ✔, Любая платформа, Почта привязана, Любой, Нероленный, AR 50, Ивент 60, Стандарт 100, Примогемы 55000",
    "price": 51,
    "oldPrice": 2000,
    "url": "https://funpay.com/lots/offer?id=15930662",
    "time": 31
  },
  {
    "id": 1114734,
    "game": "genshin",
    "platform": "funpay",
    "title": "AR 60 | Е2 Фаенон,керидра,Саня+сигна,Яо ; 22 Легендарок, 70ур освоения полный доступ, Любая платформа, Почта не привязана, Любой, Прокачанный, AR 60",
    "price": 51,
    "oldPrice": 2000,
    "url": "https://funpay.com/lots/offer?id=67381016",
    "time": 33
  },
  {
    "id": 6213415,
    "game": "genshin",
    "platform": "funpay",
    "title": "AR 59 | Колумбина с1+сигна, нефер , ху тао с1 +сигна +скин и т.д,, Любая платформа, Почта привязана, Итэр, Прокачанный, AR 59, Ивент 15, Стандарт 8, Примогемы 344",
    "price": 51,
    "oldPrice": 2000,
    "url": "https://funpay.com/lots/offer?id=67676707",
    "time": 35
  },
  {
    "id": 2053026,
    "game": "genshin",
    "platform": "funpay",
    "title": "AR 57 | ЕВРОПА АВТОВЫДАЧА КОКОМИ, Е ЛАНЬ, ЭОЛА, ЧАСКА, МУАЛАНИ, ЛИНИ И ДР СРАЗУ С ПОЧНОЙ 57 AR, Любая платформа, Почта привязана, Любой, Прокачанный, AR 57",
    "price": 51,
    "oldPrice": 2000,
    "url": "https://funpay.com/lots/offer?id=52825271",
    "time": 37
  },
  {
    "id": 8541380,
    "game": "genshin",
    "platform": "funpay",
    "title": "AR 53 | ૮ Ꮚ ◜ᴗ◝ ა 🐾 12 ЛЕГ. ВАРЕСА + СИГНА, ЧЖУН ЛИ, ХУ ТАО, РАЙДЕН, ИТТО, ПОСОХ АЛЫХ ПЕСКОВ и тд., Любая платформа, Почта привязана, Люмин, Прокачанный, AR 53",
    "price": 51,
    "oldPrice": 2000,
    "url": "https://funpay.com/lots/offer?id=68323136",
    "time": 39
  },
  {
    "id": 7315651,
    "game": "genshin",
    "platform": "funpay",
    "title": "AR 55 | 🔻 АВТОВЫДАЧА 🔺 ❥❥ Кирилл Чудомирович Флинс 49500+ ПРИМОГЕМОВ 60+ события круто ❥, Любая платформа, Почта привязана, Любой, Нероленный, AR 55, Ивент 60, Стандарт 100, Примогемы 49500",
    "price": 51,
    "oldPrice": 2000,
    "url": "https://funpay.com/lots/offer?id=62184532",
    "time": 41
  },
  {
    "id": 2611302,
    "game": "genshin",
    "platform": "funpay",
    "title": "AR 55 | 🔻 АВТОВЫДАЧА 🔺 ❥❥ Вареса 58500+ ПРИМОГЕМОВ 60+ события круто 100+ стандартным круто ❥, Любая платформа, Почта привязана, Любой, Нероленный, AR 55, Ивент 60, Стандарт 100, Примогемы 58500",
    "price": 51,
    "oldPrice": 2000,
    "url": "https://funpay.com/lots/offer?id=62183912",
    "time": 43
  },
  {
    "id": 3137302,
    "game": "genshin",
    "platform": "funpay",
    "title": "AR 57 | ЛИЧНЫЙ АККАУНТ57 AR 🌠19 ЛЕГ🌠 🔹 Аяка + Сигна | Нахида + Сигна | Клоринда + Сигна🔹, Любая платформа, Почта привязана, Итэр, Прокачанный, AR 57",
    "price": 51,
    "oldPrice": 2000,
    "url": "https://funpay.com/lots/offer?id=67460343",
    "time": 45
  },
  {
    "id": 9056303,
    "game": "genshin",
    "platform": "funpay",
    "title": "AR 56 | Продам личный аккаунт! Флинс, Тигнари с2, Мидзуки, Елань. 18 лег, Любая платформа, Почта привязана, Люмин, Прокачанный, AR 56",
    "price": 51,
    "oldPrice": 2000,
    "url": "https://funpay.com/lots/offer?id=58903488",
    "time": 47
  },
  {
    "id": 2308505,
    "game": "genshin",
    "platform": "funpay",
    "title": "AR 59 | аккаунт с 2021 года 59 ранг, Любая платформа, Почта привязана, Люмин, Прокачанный, AR 59",
    "price": 51,
    "oldPrice": 2000,
    "url": "https://funpay.com/lots/offer?id=68731170",
    "time": 49
  }
]