[
  {
    "id": 684928,
    "game": "genshin",
    "platform": "funpay",
    "title": "AR 57 | 💟АВТОВЫДАЧА💟37 Персонажей9 Лег57 AR2 Легендарных Оружия3 Созвездий На Легендарках8 LVL Мира, Любая платформа, Почта привязана, Люмин, Прокачанный, AR 57, Примогемы 477",
    "price": 50,
    "oldPrice": 2000,
    "url": "https://funpay.com/lots/offer?id=53395846",
    "time": 1
  },
  {
    "id": 9872294,
    "game": "genshin",
    "platform": "funpay",
    "title": "AR 58 | ˏˋ ⚪ genshin 19 лег + honkai 16лег ⚪ Кинич Бай Чжу Часка Мавуика Коломбина Лаума Фурина, Любая платформа, Почта привязана, Итэр, Прокачанный, AR 58, Ивент 14, Стандарт 5, Примогемы 3000",
    "price": 50,
    "oldPrice": 2000,
    "url": "https://funpay.com/lots/offer?id=68332864",
    "time": 3
  },
  {
    "id": 6100496,
    "game": "genshin",
    "platform": "funpay",
    "title": "AR 58 | [ 58AR] · Райдэн C3 + Сигна, Эола, Фурина, Арлекино, Гань Юй, Ху Тао, Аяка, Яэ Мико, Е Лань· , Любая платформа, Почта привязана, Люмин, Прокачанный, AR 58, Ивент 12, Стандарт 5",
    "price": 50,
    "oldPrice": 2000,
    "url": "https://funpay.com/lots/offer?id=16657505",
    "time": 5
  },
  {
    "id": 2660928,
    "game": "genshin",
    "platform": "funpay",
    "title": "AR 57 | ASIA|AR 57|10 limit+2sign|Zibai,Linnea,Xilonen+sign,Raiden+sign,|MC Female|Check SS|GI156B, Любая платформа, Почта привязана, Любой, Нероленный, AR 50",
    "price": 50,
    "oldPrice": 2000,
    "url": "https://funpay.com/lots/offer?id=68330239",
    "time": 7
  },
  {
    "id": 9669762,
    "game": "genshin",
    "platform": "funpay",
    "title": "AR 56 | ASIA | AR.LV 56, Characters: 33, Achievements: 415 [FullAccess] | Fast Delivery, PC, AR 56",
    "price": 50,
    "oldPrice": 2000,
    "url": "https://funpay.com/lots/offer?id=11210558",
    "time": 9
  },
  {
    "id": 6922762,
    "game": "wuwa",
    "platform": "funpay",
    "title": "🔴🔴🔴 ПОДПИСКА НА 6 МЕСЯЦЕВ ▪︎ УКРАИНА ▪︎ ( ДРУГОЙ РЕГИОН - В ЛС ) 🔴🔴🔴, UA, Подписка на 6 месяцев",
    "price": 50,
    "oldPrice": 1000,
    "url": "https://funpay.com/lots/offer?id=49656184",
    "time": 11
  },
  {
    "id": 3742117,
    "game": "wuwa",
    "platform": "funpay",
    "title": "🕹🎮 [ Battle. Net ] 🎮🕹 ПОДПИСКА WOW 6 Месяцев 🟡 [ Украина ] 🟡, UA, Подписка на 6 месяцев",
    "price": 50,
    "oldPrice": 1000,
    "url": "https://funpay.com/lots/offer?id=40869654",
    "time": 13
  },
  {
    "id": 2115306,
    "game": "wuwa",
    "platform": "funpay",
    "title": "🎮Подписка на 6 месяцев (UAH Украина, Другой регион? В ЛС) На ваш аккаунт🎮, UA, Подписка на 6 месяцев",
    "price": 50,
    "oldPrice": 1000,
    "url": "https://funpay.com/lots/offer?id=23297683",
    "time": 15
  },
  {
    "id": 6846513,
    "game": "wuwa",
    "platform": "funpay",
    "title": "✅✅✅ 6 МЕСЯЦЕВ ✅✅✅ ПОДПИСКА ДЛЯ WORLD OF WARCRAFT ✅✅✅Украина✅✅✅, UA, Подписка на 6 месяцев",
    "price": 50,
    "oldPrice": 1000,
    "url": "https://funpay.com/lots/offer?id=60350121",
    "time": 17
  },
  {
    "id": 7327982,
    "game": "wuwa",
    "platform": "funpay",
    "title": "✅ Европа 3 месяца подписки ✅, EU, Подписка на 3 месяца",
    "price": 50,
    "oldPrice": 1000,
    "url": "https://funpay.com/lots/offer?id=67709553",
    "time": 19
  },
  {
    "id": 1203941,
    "game": "wuwa",
    "platform": "funpay",
    "title": "🔵🟡🎮❗БЕЗ ВХОДА❗ Подписка на 6 месяцев/180 дней 🇺🇦Украина🇺🇦🎮🔵🟡, UA, Подписка на 6 месяцев",
    "price": 50,
    "oldPrice": 1000,
    "url": "https://funpay.com/lots/offer?id=29966523",
    "time": 21
  },
  {
    "id": 4510402,
    "game": "wuwa",
    "platform": "funpay",
    "title": "⛳FAST NOW⛳︵‿୨୧‿︵⏰⏰⏰World of Warcraft®: Подписка 6 мес. 🍒Украина🍒[На мой\\Ваш аккаунт]🍒, UA, Подписка на 6 месяцев",
    "price": 50,
    "oldPrice": 1000,
    "url": "https://funpay.com/lots/offer?id=14788675",
    "time": 23
  },
  {
    "id": 9997588,
    "game": "wuwa",
    "platform": "funpay",
    "title": "World of Warcraft®: ПОДПИСКА НА 6 МЕСЯЦ Турция, TR, Подписка на 6 месяцев",
    "price": 50,
    "oldPrice": 1000,
    "url": "https://funpay.com/lots/offer?id=60058387",
    "time": 25
  },
  {
    "id": 7943244,
    "game": "wuwa",
    "platform": "funpay",
    "title": "🍁Подписка 180 дней, регион Украина🍁, UA, Подписка на 6 месяцев",
    "price": 50,
    "oldPrice": 1000,
    "url": "https://funpay.com/lots/offer?id=14728112",
    "time": 27
  },
  {
    "id": 5534345,
    "game": "genshin",
    "platform": "funpay",
    "title": "AR 57 | Р57 Европа | Люмин 7 Ивент | Р57 + АКК в ЗЗЗ Р57 Европа | Белль 8 ИвентТорг Уместен, Любая платформа, Почта привязана, Люмин, Прокачанный, AR 57, Ивент 7",
    "price": 51,
    "oldPrice": 2000,
    "url": "https://funpay.com/lots/offer?id=64697952",
    "time": 29
  },
  {
    "id": 1746968,
    "game": "genshin",
    "platform": "funpay",
    "title": "AR 48 | 💕АВТОВЫДАЧА💕240 КМ Арлекино С3/C3 + Нефритовый коршунФуринаНавияДжиннМонаДилюк, Любая платформа, Почта привязана, Люмин, Прокачанный, AR 48",
    "price": 51,
    "oldPrice": 2000,
    "url": "https://funpay.com/lots/offer?id=60057535",
    "time": 31
  },
  {
    "id": 9723144,
    "game": "genshin",
    "platform": "funpay",
    "title": "AR 50 | HONKAI STAR RAIL + GENSHIN IMPACT , Любая платформа, Почта привязана, Люмин, Прокачанный, AR 50",
    "price": 51,
    "oldPrice": 2000,
    "url": "https://funpay.com/lots/offer?id=43220836",
    "time": 33
  },
  {
    "id": 3407579,
    "game": "genshin",
    "platform": "funpay",
    "title": "AR 59 | 🔱 59 AR 🔱 26 Лег 🔱 Ху Тао С2+сигна 🔱 Аль-Хайтам + сигна 🔱 Лаума 🔱 Коломбина 🔱 Е Лань 🔱 Нёвиллет 🔱, Любая платформа, Почта привязана, Люмин, Прокачанный, AR 59, Ивент 50, Стандарт 5",
    "price": 51,
    "oldPrice": 2000,
    "url": "https://funpay.com/lots/offer?id=67624591",
    "time": 35
  },
  {
    "id": 8241706,
    "game": "genshin",
    "platform": "funpay",
    "title": "AR 56 | с6р1 фурина 95 лвл + шилонен р1 + арлекино, Любая платформа, Почта привязана, Люмин, Прокачанный, AR 56",
    "price": 51,
    "oldPrice": 2000,
    "url": "https://funpay.com/lots/offer?id=68304438",
    "time": 37
  },
  {
    "id": 871961,
    "game": "genshin",
    "platform": "funpay",
    "title": "AR 55 | 🍁18 ЛЕГ🍁Арлекино Бай Чжу Яэ Мико Кадзуха Невиллет Странник Гань ЮЙ Чжун Ли Аяка+ см. описание, Любая платформа, Почта привязана, Итэр, Прокачанный, AR 55, Ивент 9, Стандарт 7",
    "price": 51,
    "oldPrice": 2000,
    "url": "https://funpay.com/lots/offer?id=59644768",
    "time": 39
  },
  {
    "id": 7321244,
    "game": "genshin",
    "platform": "funpay",
    "title": "AR 58 | 58 AR Флинс+сигна,Инефа, Сайноc1+сигна,Ху тоc1+сигна Луна 112дней и др., Любая платформа, Почта привязана, Итэр, Прокачанный, AR 58, Ивент 12, Стандарт 4",
    "price": 51,
    "oldPrice": 2000,
    "url": "https://funpay.com/lots/offer?id=67591407",
    "time": 41
  },
  {
    "id": 4240512,
    "game": "genshin",
    "platform": "funpay",
    "title": "AR 58 | AR 58 невиллетт + сигна; Вареса C1, сяо + Сигна, Муалани, Райден, Арлекино, Йелан, Инеффа, Дурин, Любая платформа, Почта не привязана, Люмин, Прокачанный, AR 58",
    "price": 51,
    "oldPrice": 2000,
    "url": "https://funpay.com/lots/offer?id=66387250",
    "time": 43
  },
  {
    "id": 7983024,
    "game": "genshin",
    "platform": "funpay",
    "title": "AR 59 | Продаю аккаунт с Колумбиной и другие леги, сигна колумбины и казаха, Любая платформа, Почта привязана, Люмин, Прокачанный, AR 59",
    "price": 51,
    "oldPrice": 2000,
    "url": "https://funpay.com/lots/offer?id=67100986",
    "time": 45
  },
  {
    "id": 2525644,
    "game": "genshin",
    "platform": "funpay",
    "title": "AR 55 | ‍ЛИЧНЫЙ АККАУНТ 12лег‍МавуикаХу Тао+ СкинФуринаСяоРайдэнНефер, Любая платформа, Почта привязана, Итэр, Прокачанный, AR 55",
    "price": 51,
    "oldPrice": 2000,
    "url": "https://funpay.com/lots/offer?id=55398002",
    "time": 47
  },
  {
    "id": 9328017,
    "game": "wuwa",
    "platform": "funpay",
    "title": "🟪World of Warcraft]🗝[Подписка 3 месяца]🗝🔴[Турция🟪, TR, Подписка на 3 месяца",
    "price": 51,
    "oldPrice": 1000,
    "url": "https://funpay.com/lots/offer?id=38151803",
    "time": 49
  }
]